{
  "AI-Improvements-1.20-0.5.2.jar": {
    "modId": "aiimprovements",
    "version": "0.5.2"
  },
  "alexscaves-2.0.2.jar": {
    "modId": "alexscaves",
    "version": "2.0.2"
  },
  "alexsmobs-1.22.9.jar": {
    "modId": "alexsmobs",
    "version": "1.22.9"
  },
  "almostunified-forge-1.20.1-0.9.4.jar": {
    "modId": "almostunified",
    "version": "1.20.1-0.9.4"
  },
  "AmbientSounds_FORGE_v6.1.6_mc1.20.1.jar": {
    "modId": "ambientsounds",
    "version": "6.1.6"
  },
  "Aquaculture-1.20.1-2.5.5.jar": {
    "modId": "aquaculture",
    "version": "2.5.5"
  },
  "architectury-9.2.14-forge.jar": {
    "modId": "architectury",
    "version": "9.2.14"
  },
  "atmospheric-1.20.1-6.1.0.jar": {
    "modId": "atmospheric",
    "version": "6.1.0"
  },
  "AttributeFix-Forge-1.20.1-21.0.4.jar": {
    "modId": "attributefix",
    "version": "21.0.4"
  },
  "autumnity-1.20.1-5.0.2.jar": {
    "modId": "autumnity",
    "version": "5.0.2"
  },
  "balm-forge-1.20.1-7.3.20-all.jar": {
    "modId": "balm",
    "version": "7.3.20"
  },
  "bellsandwhistles-0.4.5-1.20.x-Create6.0+.jar": {
    "modId": "bellsandwhistles",
    "version": "0.4.3-1.20.x"
  },
  "BetterCompatibilityChecker-forge-4.0.8+mc1.20.1.jar": {
    "modId": "bcc",
    "version": "4.0.8"
  },
  "BiomesOPlenty-1.20.1-18.0.0.592.jar": {
    "modId": "biomesoplenty",
    "version": "18.0.0.592"
  },
  "bjornlib-forge-1.0.19.5-1.20.1.jar": {
    "modId": "bjornlib",
    "version": "1.0.19.5"
  },
  "blueprint-1.20.1-7.1.2.jar": {
    "modId": "blueprint",
    "version": "7.1.2"
  },
  "botarium-forge-1.20.1-2.3.4.jar": {
    "modId": "botarium",
    "version": "2.3.4"
  },
  "cfwinfo-1.4.0.jar": {
    "modId": "cfwinfo",
    "version": "1.4.0"
  },
  "citadel-2.6.1-1.20.1.jar": {
    "modId": "citadel",
    "version": "2.6.1"
  },
  "Clumps-forge-1.20.1-12.0.0.4.jar": {
    "modId": "clumps",
    "version": "12.0.0.4"
  },
  "configured-forge-1.20.1-2.2.3.jar": {
    "modId": "configured",
    "version": "2.2.3"
  },
  "connectivity-1.20.1-7.1.jar": {
    "modId": "connectivity",
    "version": "1.20.1-7.1"
  },
  "Controlling-forge-1.20.1-12.0.2.jar": {
    "modId": "controlling",
    "version": "12.0.2"
  },
  "coroutil-forge-1.20.1-1.3.7.jar": {
    "modId": "coroutil",
    "version": "1.20.1-1.3.7"
  },
  "corpse-forge-1.20.1-1.0.20.jar": {
    "modId": "corpse",
    "version": "1.20.1-1.0.20"
  },
  "crash_assistant-forge-1.4.3.jar": {
    "modId": "crash_assistant",
    "version": "1.4.3"
  },
  "CraterLib-Forge-1.20-2.1.3.jar": {
    "modId": "craterlib",
    "version": "2.1.3"
  },
  "create-1.20.1-6.0.4.jar": {
    "modId": "create",
    "version": "6.0.4"
  },
  "create-new-age-forge-1.20.1-1.1.3.jar": {
    "modId": "create_new_age",
    "version": "1.1.3"
  },
  "create-stuff-additions1.20.1_v2.0.9.jar": {
    "modId": "create_sa",
    "version": "2.0.9"
  },
  "create_compressed-2.1.0-forge-1.20.1.jar": {
    "modId": "create_compressed",
    "version": "2.1.0"
  },
  "create_enchantment_industry-1.3.2-for-create-6.0.3.jar": {
    "modId": "create_enchantment_industry",
    "version": "1.3.2-for-create-6.0.3"
  },
  "create_ltab_f-2.5.2.jar": {
    "modId": "create_ltab_f",
    "version": "2.5.2"
  },
  "create_misc_and_things_ 1.20.1_4.0A.jar": {
    "modId": "create_things_and_misc",
    "version": "1.0.0"
  },
  "Create_Questing-FORGE-1.20.1-1.0.0.jar": {
    "modId": "create_questing",
    "version": "1.0.0"
  },
  "create_snt-0.6.9_forge.jar": {
    "modId": "create_snt",
    "version": "0.6.9"
  },
  "create_tweaked_controllers-1.20.1-1.2.5.jar": {
    "modId": "create_tweaked_controllers",
    "version": "1.20.1-1.2.5"
  },
  "create_ultimate_factory-1.9.0-forge-1.20.1.jar": {
    "modId": "create_ultimate_factory",
    "version": "1.9.0"
  },
  "create_winery-1.4.0-forge-1.20.1.jar": {
    "modId": "create_winery",
    "version": "1.4.0"
  },
  "createaddition-1.20.1-1.3.1.jar": {
    "modId": "createaddition",
    "version": "1.20.1-1.3.1"
  },
  "createliquidfuel-2.1.1-1.20.1.jar": {
    "modId": "createliquidfuel",
    "version": "2.1.1-1.20.1"
  },
  "CreateNumismatics-1.0.15+forge-mc1.20.1.jar": {
    "modId": "numismatics",
    "version": "1.0.15+forge-mc1.20.1"
  },
  "createoreexcavation-1.20-1.6.2.jar": {
    "modId": "createoreexcavation",
    "version": "1.6.2"
  },
  "createtaczauto-1.3.7-forge-1.20.1.jar": {
    "modId": "createtaczauto",
    "version": "1.3.7"
  },
  "CreativeCore_FORGE_v2.12.31_mc1.20.1.jar": {
    "modId": "creativecore",
    "version": "2.12.31"
  },
  "cupboard-1.20.1-2.7.jar": {
    "modId": "cupboard",
    "version": "1.20.1-2.7"
  },
  "darkness-forge-1.20.1-2.0.103-fork.jar": {
    "modId": "darkness",
    "version": "2.0.103"
  },
  "DistantHorizons-fabric-forge-2.3.0-b-1.20.1.jar": {
    "modId": "distanthorizons",
    "version": "2.3.0-b"
  },
  "entity_model_features_forge_1.20.1-2.4.1.jar": {
    "modId": "entity_model_features",
    "version": "2.4.1"
  },
  "entity_texture_features_forge_1.20.1-6.2.9.jar": {
    "modId": "entity_texture_features",
    "version": "6.2.9"
  },
  "entityculling-forge-1.7.3-mc1.20.1.jar": {
    "modId": "entityculling",
    "version": "1.7.3"
  },
  "environmental-1.20.1-4.0.1.jar": {
    "modId": "environmental",
    "version": "4.0.1"
  },
  "FastLeafDecay-32.jar": {
    "modId": "fastleafdecay",
    "version": "32"
  },
  "ferritecore-6.0.1-forge.jar": {
    "modId": "ferritecore",
    "version": "6.0.1"
  },
  "ftb-library-forge-2001.2.9.jar": {
    "modId": "ftblibrary",
    "version": "2001.2.9"
  },
  "ftb-quests-forge-2001.4.12.jar": {
    "modId": "ftbquests",
    "version": "2001.4.12"
  },
  "ftb-teams-forge-2001.3.1.jar": {
    "modId": "ftbteams",
    "version": "2001.3.1"
  },
  "fusion-1.2.5-forge-mc1.20.1.jar": {
    "modId": "fusion",
    "version": "1.2.5"
  },
  "geckolib-forge-1.20.1-4.7.1.1.jar": {
    "modId": "geckolib",
    "version": "4.7.1.1"
  },
  "GlitchCore-forge-1.20.1-0.0.1.1.jar": {
    "modId": "glitchcore",
    "version": "0.0.1.1"
  },
  "gpumemleakfix-1.20.1-1.8.jar": {
    "modId": "gpumemleakfix",
    "version": "1.20.1-1.8"
  },
  "interiors-0.5.6+forge-mc1.20.1-local.jar": {
    "modId": "interiors",
    "version": "0.5.6"
  },
  "Jade-1.20.1-Forge-11.12.3.jar": {
    "modId": "jade",
    "version": "11.12.3+forge"
  },
  "jeed-1.20-2.2.5.jar": {
    "modId": "jeed",
    "version": "1.20-2.2.5"
  },
  "jei-1.20.1-forge-15.20.0.106.jar": {
    "modId": "jei",
    "version": "15.20.0.106"
  },
  "journeymap-1.20.1-5.10.3-forge.jar": {
    "modId": "journeymap",
    "version": "5.10.3"
  },
  "justenoughbreeding-forge-1.20-1.20.1-1.5.0.jar": {
    "modId": "justenoughbreeding",
    "version": "1.5.0"
  },
  "JustEnoughProfessions-forge-1.20.1-3.0.1.jar": {
    "modId": "justenoughprofessions",
    "version": "3.0.1"
  },
  "JustEnoughResources-1.20.1-1.4.0.247.jar": {
    "modId": "jeresources",
    "version": "1.4.0.247"
  },
  "kotlinforforge-4.11.0-all.jar": {},
  "kubejs-forge-2001.6.5-build.16.jar": {
    "modId": "kubejs",
    "version": "2001.6.5-build.16"
  },
  "lootr-forge-1.20-0.7.35.90.jar": {
    "modId": "lootr",
    "version": "0.7.35.90"
  },
  "mcw-bridges-3.0.0-mc1.20.1forge.jar": {
    "modId": "mcwbridges",
    "version": "3.0.0"
  },
  "mcw-fences-1.1.2-mc1.20.1forge.jar": {
    "modId": "mcwfences",
    "version": "1.1.2"
  },
  "mcw-roofs-2.3.1-mc1.20.1forge.jar": {
    "modId": "mcwroofs",
    "version": "2.3.1"
  },
  "modernfix-forge-5.20.2+mc1.20.1.jar": {
    "modId": "modernfix",
    "version": "5.20.2+mc1.20.1"
  },
  "molten_vents-1.20.1-2.0.9.jar": {
    "modId": "molten_vents",
    "version": "2.0.9"
  },
  "moonlight-1.20-2.13.79-forge.jar": {
    "modId": "moonlight",
    "version": "1.20-2.13.79"
  },
  "Necronomicon-Forge-1.6.0+1.20.1.jar": {
    "modId": "necronomicon",
    "version": "1.6.0"
  },
  "netherportalfix-forge-1.20-13.0.1.jar": {
    "modId": "netherportalfix",
    "version": "13.0.1"
  },
  "NoChatReports-FORGE-1.20.1-v2.2.2.jar": {
    "modId": "nochatreports",
    "version": "1.20.1-v2.2.2"
  },
  "opacpvp-forge-1.0.1-1.20.1.jar": {
    "modId": "opacpvp",
    "version": "1.0.0"
  },
  "open-parties-and-claims-forge-1.20.1-0.24.0.jar": {
    "modId": "openpartiesandclaims",
    "version": "0.24.0"
  },
  "PickUpNotifier-v8.0.0-1.20.1-Forge.jar": {
    "modId": "pickupnotifier",
    "version": "8.0.0"
  },
  "PuzzlesLib-v8.1.29-1.20.1-Forge.jar": {
    "modId": "puzzleslib",
    "version": "8.1.29"
  },
  "Quark-4.0-461.jar": {
    "modId": "quark",
    "version": "4.0-461"
  },
  "rhino-forge-2001.2.3-build.10.jar": {
    "modId": "rhino",
    "version": "2001.2.3-build.10"
  },
  "Searchables-forge-1.20.1-1.0.3.jar": {
    "modId": "searchables",
    "version": "1.0.3"
  },
  "SereneSeasons-forge-1.20.1-9.1.0.1.jar": {
    "modId": "sereneseasons",
    "version": "9.1.0.1"
  },
  "SimpleRPC-Universal-3.3.3.jar": {
    "modId": "simplerpc",
    "version": "3.3.3"
  },
  "sliceanddice-forge-3.4.0.jar": {
    "modId": "sliceanddice",
    "version": "3.4.0"
  },
  "smoothchunk-1.20.1-4.1.jar": {
    "modId": "smoothchunk",
    "version": "1.20.1-4.1"
  },
  "sound-physics-remastered-forge-1.20.1-1.4.8.jar": {
    "modId": "sound_physics_remastered",
    "version": "1.20.1-1.4.8"
  },
  "supermartijn642configlib-1.1.8-forge-mc1.20.jar": {
    "modId": "supermartijn642configlib",
    "version": "1.1.8"
  },
  "supermartijn642corelib-1.1.18-forge-mc1.20.1.jar": {
    "modId": "supermartijn642corelib",
    "version": "1.1.18"
  },
  "supplementaries-1.20-3.1.20.jar": {
    "modId": "supplementaries",
    "version": "1.20-3.1.20"
  },
  "tacz-1.20.1-1.1.4-hotfix-all.jar": {
    "modId": "tacz",
    "version": "1.1.4-hotfix"
  },
  "tacz_c-1.0.1-forge-1.20.1.jar": {
    "modId": "tacz_c",
    "version": "1.0.1"
  },
  "TerraBlender-forge-1.20.1-3.0.1.10.jar": {
    "modId": "terrablender",
    "version": "3.0.1.10"
  },
  "Terralith_1.20.x_v2.5.4.jar": {
    "modId": "terralith",
    "version": "2.5.4"
  },
  "ThirstWasTaken-1.20.1-1.3.16.jar": {
    "modId": "thirst",
    "version": "1.20.1-1.3.16"
  },
  "toms_storage-1.20-1.7.0.jar": {
    "modId": "toms_storage",
    "version": "1.7.0"
  },
  "VisualWorkbench-v8.0.0-1.20.1-Forge.jar": {
    "modId": "visualworkbench",
    "version": "8.0.0"
  },
  "voicechat-forge-1.20.1-2.5.26.jar": {
    "modId": "voicechat",
    "version": "1.20.1-2.5.26"
  },
  "watut-forge-1.20.1-1.2.3.jar": {
    "modId": "watut",
    "version": "1.20.1-1.2.3"
  },
  "waystones-forge-1.20.1-14.1.11.jar": {
    "modId": "waystones",
    "version": "14.1.11"
  },
  "worldedit-mod-7.2.15.jar": {
    "modId": "worldedit",
    "version": "7.2.15+6463-5ca4dff"
  },
  "xlpackets-1.18.2-2.1.jar": {
    "modId": "xlpackets",
    "version": "1.18.2-2.1"
  },
  "YungsApi-1.20-Forge-4.0.6.jar": {
    "modId": "yungsapi",
    "version": "1.20-Forge-4.0.6"
  },
  "YungsBetterDesertTemples-1.20-Forge-3.0.3.jar": {
    "modId": "betterdeserttemples",
    "version": "1.20-Forge-3.0.3"
  },
  "YungsBetterDungeons-1.20-Forge-4.0.4.jar": {
    "modId": "betterdungeons",
    "version": "1.20-Forge-4.0.4"
  },
  "YungsBetterEndIsland-1.20-Forge-2.0.6.jar": {
    "modId": "betterendisland",
    "version": "1.20-Forge-2.0.6"
  },
  "YungsBetterJungleTemples-1.20-Forge-2.0.5.jar": {
    "modId": "betterjungletemples",
    "version": "1.20-Forge-2.0.5"
  },
  "YungsBetterMineshafts-1.20-Forge-4.0.4.jar": {
    "modId": "bettermineshafts",
    "version": "1.20-Forge-4.0.4"
  },
  "YungsBetterNetherFortresses-1.20-Forge-2.0.6.jar": {
    "modId": "betterfortresses",
    "version": "1.20-Forge-2.0.6"
  },
  "YungsBetterOceanMonuments-1.20-Forge-3.0.4.jar": {
    "modId": "betteroceanmonuments",
    "version": "1.20-Forge-3.0.4"
  },
  "YungsBetterStrongholds-1.20-Forge-4.0.3.jar": {
    "modId": "betterstrongholds",
    "version": "1.20-Forge-4.0.3"
  },
  "YungsBetterWitchHuts-1.20-Forge-3.0.3.jar": {
    "modId": "betterwitchhuts",
    "version": "1.20-Forge-3.0.3"
  },
  "YungsBridges-1.20-Forge-4.0.3.jar": {
    "modId": "yungsbridges",
    "version": "1.20-Forge-4.0.3"
  },
  "YungsExtras-1.20-Forge-4.0.3.jar": {
    "modId": "yungsextras",
    "version": "1.20-Forge-4.0.3"
  },
  "Zeta-1.0-28.jar": {
    "modId": "zeta",
    "version": "1.0-28"
  },
  "zombieawareness-1.20.1-1.13.1.jar": {
    "modId": "zombieawareness",
    "version": "1.20.1-1.13.1"
  }
}